README.md
setup.py
hbp_seafile/__init__.py
hbp_seafile/access.py
hbp_seafile/admin.py
hbp_seafile/client.py
hbp_seafile/exceptions.py
hbp_seafile/files.py
hbp_seafile/group.py
hbp_seafile/repo.py
hbp_seafile/repos.py
hbp_seafile/utils.py
hbp_seafile.egg-info/PKG-INFO
hbp_seafile.egg-info/SOURCES.txt
hbp_seafile.egg-info/dependency_links.txt
hbp_seafile.egg-info/requires.txt
hbp_seafile.egg-info/top_level.txt
tests/__init__.py
tests/conftest.py
tests/fixtures.py
tests/test_files.py
tests/test_repos.py
tests/utils.py