Metadata-Version: 1.1
Name: hbp-seafile
Version: 0.1.1
Summary: Python client interface for HBP Collaboratory Seafile storage
Home-page: http://seafile.com
Author: Shuai Lin, Shailesh Appukuttan
Author-email: linshuai2012@gmail.com, appukuttan.shailesh@gmail.com
License: Apache-2.0 License
Platform: Any
Classifier: Development Status :: 4 - Beta
Classifier: License :: OSI Approved :: BSD License
Classifier: Operating System :: OS Independent
Classifier: Programming Language :: Python
